metaphor_machine/__init__.py
metaphor_machine/cli/__init__.py
metaphor_machine/cli/main.py
metaphor_machine/core/__init__.py
metaphor_machine/core/generator.py
metaphor_machine/core/metaphor.py
metaphor_machine/corpus/__init__.py
metaphor_machine/corpus/storage.py
metaphor_machine/optimization/__init__.py
metaphor_machine/optimization/bayesian.py
metaphor_machine/optimization/fitness.py
metaphor_machine/optimization/genetic.py
metaphor_machine/schemas/__init__.py
metaphor_machine/schemas/components.py
metaphor_machine/schemas/config.py
metaphor_machine/utils/__init__.py
metaphor_machine/utils/formatting.py
metaphor_machine/utils/validation.py
metaphor_machine-1.0.1.dist-info/METADATA
metaphor_machine-1.0.1.dist-info/WHEEL
metaphor_machine-1.0.1.dist-info/entry_points.txt
metaphor_machine-1.0.1.dist-info/licenses/LICENSE
metaphor_machine-1.0.1.dist-info/RECORD
