Metadata-Version: 2.4
Name: metaphor-machine
Version: 1.0.1
Summary: Algorithmic generation and optimization of AI music style prompts
Project-URL: Homepage, https://github.com/stayen/metaphor-machine
Project-URL: Repository, https://github.com/stayen/metaphor-machine
Project-URL: Documentation, https://github.com/stayen/metaphor-machine#readme
Project-URL: Developer, https://boyandin.com
Author-email: Konstantin Boyandin <developer@boyandin.com>
License-Expression: MIT
License-File: LICENSE
Keywords: ai-music,bayesian-optimization,generative-ai,genetic-algorithm,music-generation,optimization,prompt-engineering,suno
Classifier: Development Status :: 5 - Production/Stable
Classifier: Intended Audience :: Developers
Classifier: Intended Audience :: Science/Research
Classifier: Programming Language :: Python :: 3
Classifier: Programming Language :: Python :: 3.10
Classifier: Programming Language :: Python :: 3.11
Classifier: Programming Language :: Python :: 3.12
Classifier: Topic :: Multimedia :: Sound/Audio
Classifier: Topic :: Scientific/Engineering :: Artificial Intelligence
Requires-Python: >=3.10
Requires-Dist: click>=8.0
Requires-Dist: pydantic>=2.0
Requires-Dist: pyyaml>=6.0
Requires-Dist: rich>=13.0
Provides-Extra: all
Requires-Dist: anthropic>=0.18; extra == 'all'
Requires-Dist: librosa>=0.10; extra == 'all'
Requires-Dist: mypy>=1.0; extra == 'all'
Requires-Dist: numpy>=1.24; extra == 'all'
Requires-Dist: openai>=1.0; extra == 'all'
Requires-Dist: pytest-cov>=4.0; extra == 'all'
Requires-Dist: pytest>=7.0; extra == 'all'
Requires-Dist: ruff>=0.1.0; extra == 'all'
Requires-Dist: scipy>=1.10; extra == 'all'
Requires-Dist: sentence-transformers>=2.2; extra == 'all'
Requires-Dist: soundfile>=0.12; extra == 'all'
Requires-Dist: types-pyyaml; extra == 'all'
Provides-Extra: audio
Requires-Dist: librosa>=0.10; extra == 'audio'
Requires-Dist: soundfile>=0.12; extra == 'audio'
Provides-Extra: dev
Requires-Dist: mypy>=1.0; extra == 'dev'
Requires-Dist: pytest-cov>=4.0; extra == 'dev'
Requires-Dist: pytest>=7.0; extra == 'dev'
Requires-Dist: ruff>=0.1.0; extra == 'dev'
Requires-Dist: types-pyyaml; extra == 'dev'
Provides-Extra: embedding
Requires-Dist: sentence-transformers>=2.2; extra == 'embedding'
Provides-Extra: llm
Requires-Dist: anthropic>=0.18; extra == 'llm'
Requires-Dist: openai>=1.0; extra == 'llm'
Provides-Extra: optimization
Requires-Dist: numpy>=1.24; extra == 'optimization'
Requires-Dist: scipy>=1.10; extra == 'optimization'
